ankipan_db/__init__.py
ankipan_db/db_manager.py
ankipan_db/n_gram_collector.py
ankipan_db/source_parser.py
ankipan_db-0.6.dist-info/licenses/LICENSE
ankipan_db-0.6.dist-info/METADATA
ankipan_db-0.6.dist-info/WHEEL
ankipan_db-0.6.dist-info/top_level.txt
ankipan_db-0.6.dist-info/RECORD
